Metadata-Version: 2.1
Name: SparkySDK
Version: 0.0.3
Summary: SparkySDK
Author: RMaixtr
Author-email: 53236564@qq.com
License: MIT
Classifier: Programming Language :: Python :: 3
License-File: LICENSE
